{
    "info": {
        "name": "Duweet - Transaction Update API",
        "_postman_id": "duweet-transaction-update-001",
        "description": "Collection untuk testing endpoint update transaction Duweet API",
        "schema": "https://schema.getpostman.com/json/collection/v2.1.0/collection.json"
    },
    "item": [
        {
            "name": "1. Get All Transactions",
            "request": {
                "method": "GET",
                "header": [
                    {
                        "key": "Accept",
                        "value": "application/json",
                        "type": "text"
                    }
                ],
                "url": {
                    "raw": "http://127.0.0.1:8000/api/transactions",
                    "protocol": "http",
                    "host": [
                        "127",
                        "0",
                        "0",
                        "1"
                    ],
                    "port": "8000",
                    "path": [
                        "api",
                        "transactions"
                    ]
                },
                "description": "Get list of all transactions"
            }
        },
        {
            "name": "2. Get Transaction by ID",
            "request": {
                "method": "GET",
                "header": [
                    {
                        "key": "Accept",
                        "value": "application/json",
                        "type": "text"
                    }
                ],
                "url": {
                    "raw": "http://127.0.0.1:8000/api/transactions/1",
                    "protocol": "http",
                    "host": [
                        "127",
                        "0",
                        "0",
                        "1"
                    ],
                    "port": "8000",
                    "path": [
                        "api",
                        "transactions",
                        "1"
                    ]
                },
                "description": "Get detail of a specific transaction"
            }
        },
        {
            "name": "3. Update - All Fields",
            "request": {
                "method": "PUT",
                "header": [
                    {
                        "key": "Content-Type",
                        "value": "application/json",
                        "type": "text"
                    },
                    {
                        "key": "Accept",
                        "value": "application/json",
                        "type": "text"
                    }
                ],
                "body": {
                    "mode": "raw",
                    "raw": "{\n  \"amount\": 7500000,\n  \"description\": \"Gaji Bulanan Desember 2025 + Bonus Tahunan\",\n  \"created_at\": \"2025-12-25 09:00:00\"\n}"
                },
                "url": {
                    "raw": "http://127.0.0.1:8000/api/transactions/1",
                    "protocol": "http",
                    "host": [
                        "127",
                        "0",
                        "0",
                        "1"
                    ],
                    "port": "8000",
                    "path": [
                        "api",
                        "transactions",
                        "1"
                    ]
                },
                "description": "Update amount, description, and created_at"
            }
        },
        {
            "name": "4. Update - Amount Only",
            "request": {
                "method": "PUT",
                "header": [
                    {
                        "key": "Content-Type",
                        "value": "application/json",
                        "type": "text"
                    },
                    {
                        "key": "Accept",
                        "value": "application/json",
                        "type": "text"
                    }
                ],
                "body": {
                    "mode": "raw",
                    "raw": "{\n  \"amount\": 3500000\n}"
                },
                "url": {
                    "raw": "http://127.0.0.1:8000/api/transactions/2",
                    "protocol": "http",
                    "host": [
                        "127",
                        "0",
                        "0",
                        "1"
                    ],
                    "port": "8000",
                    "path": [
                        "api",
                        "transactions",
                        "2"
                    ]
                },
                "description": "Update only the amount field"
            }
        },
        {
            "name": "5. Update - Description Only",
            "request": {
                "method": "PUT",
                "header": [
                    {
                        "key": "Content-Type",
                        "value": "application/json",
                        "type": "text"
                    },
                    {
                        "key": "Accept",
                        "value": "application/json",
                        "type": "text"
                    }
                ],
                "body": {
                    "mode": "raw",
                    "raw": "{\n  \"description\": \"Pembelian Laptop ASUS ROG - Updated\"\n}"
                },
                "url": {
                    "raw": "http://127.0.0.1:8000/api/transactions/3",
                    "protocol": "http",
                    "host": [
                        "127",
                        "0",
                        "0",
                        "1"
                    ],
                    "port": "8000",
                    "path": [
                        "api",
                        "transactions",
                        "3"
                    ]
                },
                "description": "Update only the description field"
            }
        },
        {
            "name": "6. Update - Amount + Description",
            "request": {
                "method": "PUT",
                "header": [
                    {
                        "key": "Content-Type",
                        "value": "application/json",
                        "type": "text"
                    },
                    {
                        "key": "Accept",
                        "value": "application/json",
                        "type": "text"
                    }
                ],
                "body": {
                    "mode": "raw",
                    "raw": "{\n  \"amount\": 2500000,\n  \"description\": \"Belanja Bulanan di Supermarket Indomaret\"\n}"
                },
                "url": {
                    "raw": "http://127.0.0.1:8000/api/transactions/4",
                    "protocol": "http",
                    "host": [
                        "127",
                        "0",
                        "0",
                        "1"
                    ],
                    "port": "8000",
                    "path": [
                        "api",
                        "transactions",
                        "4"
                    ]
                },
                "description": "Update amount and description together"
            }
        },
        {
            "name": "7. Update - Real: Gaji",
            "request": {
                "method": "PUT",
                "header": [
                    {
                        "key": "Content-Type",
                        "value": "application/json",
                        "type": "text"
                    },
                    {
                        "key": "Accept",
                        "value": "application/json",
                        "type": "text"
                    }
                ],
                "body": {
                    "mode": "raw",
                    "raw": "{\n  \"amount\": 8500000,\n  \"description\": \"Gaji Bulan Desember + Tunjangan Hari Raya\",\n  \"created_at\": \"2025-12-01 08:00:00\"\n}"
                },
                "url": {
                    "raw": "http://127.0.0.1:8000/api/transactions/5",
                    "protocol": "http",
                    "host": [
                        "127",
                        "0",
                        "0",
                        "1"
                    ],
                    "port": "8000",
                    "path": [
                        "api",
                        "transactions",
                        "5"
                    ]
                },
                "description": "Real-world example: Update salary transaction"
            }
        },
        {
            "name": "8. Update - Real: Belanja",
            "request": {
                "method": "PUT",
                "header": [
                    {
                        "key": "Content-Type",
                        "value": "application/json",
                        "type": "text"
                    },
                    {
                        "key": "Accept",
                        "value": "application/json",
                        "type": "text"
                    }
                ],
                "body": {
                    "mode": "raw",
                    "raw": "{\n  \"amount\": 1850000,\n  \"description\": \"Belanja Bulanan: Beras 25kg, Minyak 5L, Gula 2kg, Telur 3kg\",\n  \"created_at\": \"2025-12-15 17:30:00\"\n}"
                },
                "url": {
                    "raw": "http://127.0.0.1:8000/api/transactions/6",
                    "protocol": "http",
                    "host": [
                        "127",
                        "0",
                        "0",
                        "1"
                    ],
                    "port": "8000",
                    "path": [
                        "api",
                        "transactions",
                        "6"
                    ]
                },
                "description": "Real-world example: Update grocery shopping transaction"
            }
        },
        {
            "name": "9. Test Error - Negative Amount",
            "request": {
                "method": "PUT",
                "header": [
                    {
                        "key": "Content-Type",
                        "value": "application/json",
                        "type": "text"
                    },
                    {
                        "key": "Accept",
                        "value": "application/json",
                        "type": "text"
                    }
                ],
                "body": {
                    "mode": "raw",
                    "raw": "{\n  \"amount\": -500000\n}"
                },
                "url": {
                    "raw": "http://127.0.0.1:8000/api/transactions/1",
                    "protocol": "http",
                    "host": [
                        "127",
                        "0",
                        "0",
                        "1"
                    ],
                    "port": "8000",
                    "path": [
                        "api",
                        "transactions",
                        "1"
                    ]
                },
                "description": "Test validation: Should return 422 error for negative amount"
            }
        },
        {
            "name": "10. Test Error - Invalid Date Format",
            "request": {
                "method": "PUT",
                "header": [
                    {
                        "key": "Content-Type",
                        "value": "application/json",
                        "type": "text"
                    },
                    {
                        "key": "Accept",
                        "value": "application/json",
                        "type": "text"
                    }
                ],
                "body": {
                    "mode": "raw",
                    "raw": "{\n  \"created_at\": \"30-12-2025\"\n}"
                },
                "url": {
                    "raw": "http://127.0.0.1:8000/api/transactions/1",
                    "protocol": "http",
                    "host": [
                        "127",
                        "0",
                        "0",
                        "1"
                    ],
                    "port": "8000",
                    "path": [
                        "api",
                        "transactions",
                        "1"
                    ]
                },
                "description": "Test validation: Should return 422 error for invalid date format"
            }
        },
        {
            "name": "11. Test Error - Transaction Not Found",
            "request": {
                "method": "PUT",
                "header": [
                    {
                        "key": "Content-Type",
                        "value": "application/json",
                        "type": "text"
                    },
                    {
                        "key": "Accept",
                        "value": "application/json",
                        "type": "text"
                    }
                ],
                "body": {
                    "mode": "raw",
                    "raw": "{\n  \"amount\": 1000000\n}"
                },
                "url": {
                    "raw": "http://127.0.0.1:8000/api/transactions/99999",
                    "protocol": "http",
                    "host": [
                        "127",
                        "0",
                        "0",
                        "1"
                    ],
                    "port": "8000",
                    "path": [
                        "api",
                        "transactions",
                        "99999"
                    ]
                },
                "description": "Test error: Should return 400 error for non-existent transaction"
            }
        }
    ]
}